asr/__init__.py
asr/infer.py
asr/infer_asr.py
asr/timestamp_generator.py
asr_library-0.0.6.dist-info/METADATA
asr_library-0.0.6.dist-info/WHEEL
asr_library-0.0.6.dist-info/top_level.txt
asr_library-0.0.6.dist-info/RECORD
