Metadata-Version: 2.1
Name: asr-library
Version: 0.0.6
Summary: Automatic Speech Recognition inference for wav2vec2 models
Home-page: https://github.com/neerajchhimwal/asr
Author: Neeraj Chhimwal
Author-email: neerajchhimwal21197@gmail.com
License: MIT
Platform: linux
Platform: unix
Requires-Python: >3.6
Requires-Dist: pypi-kenlm
Requires-Dist: torch (>=1.8)
Requires-Dist: python-Levenshtein
Requires-Dist: joblib
Requires-Dist: sox
